__init__.py
ytsearch.py
youtube_search2-2.1.7.dist-info/LICENSE
youtube_search2-2.1.7.dist-info/METADATA
youtube_search2-2.1.7.dist-info/WHEEL
youtube_search2-2.1.7.dist-info/top_level.txt
youtube_search2-2.1.7.dist-info/RECORD
