Metadata-Version: 2.1
Name: youtube_search2
Version: 2.1.7
Summary: a youtube_search fork with additional features and patches.
Author-email: Joe Tatusko <tatuskojc@gmail.com>
Maintainer-email: Patryk Ladocha <patrykladocha76@gmail.com>
License: This is free and unencumbered software released into the public domain.
Project-URL: Homepage, https://github.com/xNykram/youtube_search2
Project-URL: Issues, https://github.com/xNykram/youtube_search2/issues
Keywords: yt,ytsearch,youtube_search,youtube_search2,youtube-search
Classifier: Programming Language :: Python :: 3.12
Classifier: Programming Language :: Python :: 3.11
Classifier: Programming Language :: Python :: 3.10
Classifier: Programming Language :: Python :: 3.9
Classifier: Programming Language :: Python :: 3.8
Requires-Python: >=3.8
License-File: LICENSE
Requires-Dist: certifi >=2024.2.2
Requires-Dist: chardet >=5.2.0
Requires-Dist: idna >=3.6
Requires-Dist: requests >=2.31.0
Requires-Dist: urllib3 >=2.2.1
Requires-Dist: beautifulsoup4 >=4.12.3
Requires-Dist: lxml >=5.1.0
